cmsplugin_cascade/__init__.py
cmsplugin_cascade/admin.py
cmsplugin_cascade/app_settings.py
cmsplugin_cascade/apps.py
cmsplugin_cascade/cms_plugins.py
cmsplugin_cascade/cms_toolbars.py
cmsplugin_cascade/fields.py
cmsplugin_cascade/forms.py
cmsplugin_cascade/hide_plugins.py
cmsplugin_cascade/image.py
cmsplugin_cascade/mixins.py
cmsplugin_cascade/models.py
cmsplugin_cascade/models_base.py
cmsplugin_cascade/plugin_base.py
cmsplugin_cascade/render_template.py
cmsplugin_cascade/strides.py
cmsplugin_cascade/utils.py
cmsplugin_cascade/widgets.py
cmsplugin_cascade/bootstrap4/__init__.py
cmsplugin_cascade/bootstrap4/accordion.py
cmsplugin_cascade/bootstrap4/buttons.py
cmsplugin_cascade/bootstrap4/card.py
cmsplugin_cascade/bootstrap4/carousel.py
cmsplugin_cascade/bootstrap4/container.py
cmsplugin_cascade/bootstrap4/embeds.py
cmsplugin_cascade/bootstrap4/fields.py
cmsplugin_cascade/bootstrap4/grid.py
cmsplugin_cascade/bootstrap4/icon.py
cmsplugin_cascade/bootstrap4/image.py
cmsplugin_cascade/bootstrap4/jumbotron.py
cmsplugin_cascade/bootstrap4/mixins.py
cmsplugin_cascade/bootstrap4/picture.py
cmsplugin_cascade/bootstrap4/plugin_base.py
cmsplugin_cascade/bootstrap4/secondary_menu.py
cmsplugin_cascade/bootstrap4/settings.py
cmsplugin_cascade/bootstrap4/tabs.py
cmsplugin_cascade/bootstrap4/utils.py
cmsplugin_cascade/clipboard/__init__.py
cmsplugin_cascade/clipboard/admin.py
cmsplugin_cascade/clipboard/cms_plugins.py
cmsplugin_cascade/clipboard/cms_toolbars.py
cmsplugin_cascade/clipboard/forms.py
cmsplugin_cascade/clipboard/utils.py
cmsplugin_cascade/extra_fields/__init__.py
cmsplugin_cascade/extra_fields/admin.py
cmsplugin_cascade/extra_fields/config.py
cmsplugin_cascade/extra_fields/mixins.py
cmsplugin_cascade/generic/__init__.py
cmsplugin_cascade/generic/custom_snippet.py
cmsplugin_cascade/generic/heading.py
cmsplugin_cascade/generic/horizontal_rule.py
cmsplugin_cascade/generic/mixins.py
cmsplugin_cascade/generic/settings.py
cmsplugin_cascade/generic/simple_wrapper.py
djangocms_cascade-2.3.14.dist-info/LICENSE-MIT
djangocms_cascade-2.3.14.dist-info/METADATA
djangocms_cascade-2.3.14.dist-info/WHEEL
djangocms_cascade-2.3.14.dist-info/top_level.txt
djangocms_cascade-2.3.14.dist-info/RECORD
