Metadata-Version: 2.1
Name: djangocms-cascade
Version: 2.3.14
Summary: Build Single Page Applications using the Django-CMS plugin system
Home-page: https://github.com/jrief/djangocms-cascade
Author: Jacob Rief
Author-email: jacob.rief@gmail.com
License: MIT
Platform: OS Independent
Classifier: Development Status :: 5 - Production/Stable
Classifier: Environment :: Web Environment
Classifier: Intended Audience :: Developers
Classifier: License :: OSI Approved :: MIT License
Classifier: Operating System :: OS Independent
Classifier: Programming Language :: Python
Classifier: Topic :: Internet :: WWW/HTTP :: Dynamic Content
Classifier: Programming Language :: Python :: 3.8
Classifier: Programming Language :: Python :: 3.9
Classifier: Programming Language :: Python :: 3.10
Classifier: Framework :: Django :: 3.2
Classifier: Framework :: Django :: 4.0
License-File: LICENSE-MIT
Requires-Dist: django (<5,>=3.2)
Requires-Dist: django-classy-tags (>=1.0)
Requires-Dist: django-cms (<4,>=3.10)
Requires-Dist: django-entangled (>=0.5.3)
Requires-Dist: djangocms-text-ckeditor (>=4.0)
Requires-Dist: django-select2 (>=7.7)
Requires-Dist: requests
